FNBOT2/__init__.py
FNBOT2-5.3.5.dist-info/METADATA
FNBOT2-5.3.5.dist-info/WHEEL
FNBOT2-5.3.5.dist-info/top_level.txt
FNBOT2-5.3.5.dist-info/RECORD
