Metadata-Version: 2.1
Name: FNBOT2
Version: 5.3.5
Summary: BOT U KNOW
Home-page: https://www.youtube.com/
Author: TCYT
Author-email: UNKNOWN
License: UNKNOWN
Platform: UNKNOWN
Classifier: Programming Language :: Python :: 3
Classifier: License :: OSI Approved :: MIT License
Classifier: Operating System :: OS Independent
Requires-Dist: BenBotAsync
Requires-Dist: FortniteAPIAsync
Requires-Dist: PirxcyPinger
Requires-Dist: aiohttp
Requires-Dist: colorama
Requires-Dist: crayons
Requires-Dist: fortnitepy (==3.6.7)
Requires-Dist: requests
Requires-Dist: sanic (==21.6.2)
